sfio/VERSION
sfio/__init__.py
sfio/_json.py
sfio/arrow.py
sfio/atsk.py
sfio/base.py
sfio/box.py
sfio/dataurl.py
sfio/lmpdata.py
sfio/lmpdump.py
sfio/lmplog.py
sfio/pdb.py
sfio/psf.py
sfio/supported_formats.py
sfio/yaml.py
sfio/data/dimer_cis.data
sfio/data/gold_fcc.atsk
sfio/data/gold_fcc.dump
sfio/data/gold_fcc.dump.gz
sfio/data/lammps_melt.log
sfio/data/ptable.parquet
sfio/data/rotigotine.pdb
sfio/data/rotigotine.psf
sfio/func/__init__.py
sfio/func/box.py
sfio/func/rdkit.py
sfio-1.1.0.dist-info/LICENSE
sfio-1.1.0.dist-info/METADATA
sfio-1.1.0.dist-info/WHEEL
sfio-1.1.0.dist-info/top_level.txt
sfio-1.1.0.dist-info/RECORD
