Metadata-Version: 2.2
Name: sfio
Version: 1.1.0
Summary: File I/O module
Author-email: Henry Chan <hyiprc@gmail.com>
License: BSD 3-Clause License
Project-URL: Repository, https://github.com/hyiprc/sfio
Keywords: File formats,Data handling,Serialization
Classifier: Intended Audience :: Science/Research
Classifier: Programming Language :: Python :: 3
Classifier: Topic :: Scientific/Engineering
Requires-Python: >=3.7
License-File: LICENSE
Requires-Dist: numpy
Requires-Dist: pandas
Requires-Dist: pyarrow
Provides-Extra: dev
Requires-Dist: pytest; extra == "dev"
Requires-Dist: pre-commit; extra == "dev"
Requires-Dist: sphinx; extra == "dev"
